{
 "title": "1 Thing",
 "album": "Touch",
 "year": "2005-01-05",
 "lyrics": "Na, na, na, na, na, oh\nNa, na, na, na, na, oh\nNa, na, na, na, na, oh\nNa, na, na, na, na\n\nOh, been trying to let it go\nTrying to keep my eyes closed\nTrying to keep it just like before\nThe times we never even thought to speak\nDon\u2019t wanna tell you what it is\nOh wee it felt so serious\nGot me thinking just too much\nI wanna set it off, but\n\nIt's this one thing that\u2019s got me trippin'\nIt's this one thing that's got me trippin' (You did)\nThis one thing my soul may be feelin'\nIt's this one thing you did oh oh\nIt's this one thing that caught me slippin'\nIt's this one thing I want to admit it (you did)\nThis one thing and I was so with it\nIt's this one thing you did oh oh\n\nHey, we don\u2019t know each other well\nSo why I keep picking up my cell?\nMemories just keep ringing bells\nOh oh, oh oh, oh\nHear voices I don\u2019t want to understand\nMy car keys are jingling in my hand\nMy high heels are clicking towards your door\nOh oh, oh oh, oh\n\nIt's this one thing that\u2019s got me trippin'\nIt's this one thing that's got me trippin' (You did)\nThis one thing my soul may be feelin'\nIt's this one thing you did oh oh\nIt's this one thing that caught me slippin'\nIt's this one thing I want to admit it (you did)\nThis one thing and I was so with it\nIt's this one thing you did oh oh\n\nMaybe I just can\u2019t believe it\nIt\u2019s this one thing you did oh oh\nI can\u2019t deny, tired of trying\nNothing left to do but to keep on seeing you\nI\u2019m hoping you can keep a secret\nFor me, for me, for me\nBut what you did, yeah\n\nIt's this one thing that\u2019s got me trippin'\nIt's this one thing that's got me trippin' (You did)\nThis one thing my soul may be feelin'\nIt's this one thing you did oh oh\nIt's this one thing that caught me slippin'\nIt's this one thing I want to admit it (you did)\nThis one thing and I was so with it\nIt's this one thing you did oh oh\n\nOh oh oh\nOh oh oh\nOh oh oh\nOh oh oh\nNa, na, na, na, na, oh, oh\nNa, na, na, na, na, oh\nNa, na, na, na, na, oh\nNa, na, na, na, na, oh\nNa, na, na, na, na\n\nIt's this one thing that's got me trippin'\nIt's this one thing that's got me trippin' (You did)\nThis one thing my soul may be feelin'\nIt's this one thing you did oh oh\nIt's this one thing that caught me slippin'\nIt\u2019s this one thing I want to admit it (You did)\nThis one thing and I was so with it\nIt's this one thing you did oh oh\nIt's this one thing that's got me trippin'\nIt's this one thing that's got me trippin' (you did)\nThis one thing my soul may be feelin'\nIt's this one thing you did oh oh\nIt's this one thing that caught me slippin'\nIt's this one thing I want to admit it (you did)\nThis one thing and I was so with it\nIt's this one thing you did oh oh",
 "image": "https://images.genius.com/bcd41861c9e30b8d36dbaab7d6eb5967.1000x1000x1.png"
}