{
 "title": "Just Roll",
 "album": "Just Roll (Single)",
 "year": null,
 "lyrics": "When it's early in the morning\nAnd you're laying next to me\nAs the sunlight melts into your skin\nAnd you're looking so sexy\nI can't explain what you do to me\nBut don't ever let it end\nBaby, it's on\nI'm enjoying it right now\nI know what to do to make you give in\nLay back\nRelax\nI gotcha back\nI'm giving you what'cha want\nDon't cha wanna?\nI'm telling you\nWhat I'm gonna do to you to get through to you?\nCause I'm into you\nI know what to do\nI've got the flow\nSo let it show\nI'm telling you what I know\nLet's do it slow\nLet's get it on\nI'm having a situation\nStimulation meditation tells me so\n\nSo baby\nJust roll over on me\nAin't no cause to fight it\nSo come on, baby\nLet's get excited\nBaby\nJust roll over on me\nCause I've got to let you know whatcha doing to me\nWhen it's later in the evening\nAnd your body's calling me\nWhen the sun goes down\nAnd the moon is out\nAnd you're feeling so freaky\nI can't believe what'cha do to me\nBut just keep it going on, baby\nIt's on until the break of dawn\nI know  what to do to you, yeah\nLay back\nRelax\nI gotcha back\nI'm giving you what'cha want\nDont'cha wanna?\nI'm telling you\nWhat I'm gonna do to you to get through to you?\nCause I'm into you\nI know what to do\nI've got the flow\nSo let it show\nI'm telling you what I know\nLet's do it slow\nLet's get it on\nI'm having a situation\nStimulation meditation tells me so\nSo baby\nJust roll over on me\nAin't no cause to fight it\nSo come on, baby\nLet's get excited\nBaby\nJust roll over on me\nCause I've got to let you know whatcha doing to me\nWake up, baby\nIt's time\nOoh\nSo, baby\nJust roll over on me\nAin't no cause to fight it\nSo come on, baby\nLet's get excited\nBaby\nJust roll over on me\nCause I've got to let you know whatcha doing to me\nIt goes on and on\nAnd on and on\nIt goes on and on\nAnd on and on\nSo baby\nJust roll over on me\nAin't no cause to fight it\nSo come on, baby\nLet's get excited\nBaby\nJust roll over on me\nCause I've got to let you know whatcha doing to me",
 "image": "https://images.genius.com/744a3ea0c846f43ae288cacb7563eb95.600x592x1.jpg"
}