{
 "title": "Think of You",
 "album": "Usher",
 "year": "1994-08-30",
 "lyrics": "All the time I think of you\nHolding on to someone new\nDon't make me lose my mind\nSeems like I've been here before\nBaby, I can't take no more\nOf you trying to play me out, baby\n\nI feel so strange thinking about you\nAfter all the wrong you've done to me\nI can't go on feeling like I do\n'Cause my heart loves you, I'm so confused\n\nAll the time I think of you\nHolding on to someone new\nDon't make me lose my mind\nSeems like I've been here before\nBaby, I can't take no more\nOf you trying to play me out, baby\n\nDon't waste my time\nCause someone like me you'll never find\nI thought we had a good thing\nBut I was wrong and now I must move on\n\nTo another love, one that I can trust\nWith my heart, I know she'll never run away\nJust can't talk no more, so I'm out the door\nTalk to me, why you wanna play love games?\n\nAll the time I think of you\nHolding on to someone new\nDon't make me lose my mind\nSeems like I've been here before\nBaby, I can't take no more\nOf you trying to play me out, baby\nAll the time I think of you\nHolding on to someone new\nDon't make me lose my mind\nSeems like I've been here before\nBaby, I can't take no more\nOf you trying to play me out, baby\n\nTo another love, one that I can trust\nWith my heart, I know she'll never run away\nJust can't talk no more, so I'm out the door\nTalk to me, why you wanna play love games?\n\nAll the time I think of you\nHolding on to someone new\nDon't make me lose my mind\nSeems like I've been here before\nBaby, I can't take no more\nOf you trying to play me out, baby\nAll the time I think of you\nHolding on to someone new\nDon't make me lose my mind\nSeems like I've been here before\nBaby, I can't take no more\nOf you trying to play me out, baby",
 "image": "https://images.genius.com/e5973f0984754d5af82a18daa7de401e.1000x986x1.jpg"
}