{
 "title": "Vibin\u2019",
 "album": "II",
 "year": "1995-09-01",
 "lyrics": "Just take a minute and catch the vibe\nJust take a minute and catch the vibe\nJust take a minute and catch the vibe\nJust take a minute and catch the vibe\n\nCoolin' in the studio you know how the story goes\nBobbin' our heads to the tune we're about to do\nIt's a laid back swing thang\nThe groove we feel is strong\nWe need peace here to get it on\nHaving fun as we go, makin' sure the flavor shows\n\nCause we're feeling alright\nTakin' our time to free our minds and have a ball, ya'll\nEverything's fine it ain't nothing to it cause\nWe're gonna do it all, what are we doin'\n\nWe're just vibin' dancing the night away\nGroovin', vibin', non-stop until the break of day\n\nOoh yeah yeah, in a dark room with a brew like\nIn the basement music just right\nNothing goin' down but the mellow sounds\nOf Mr. DJ's turntables goin' round\nA mad sensation, a crew of women around sparks inspiration\nTo set something off the right way to hear the people say\n\nThat we're feelin' alright\nTakin' our time to free our minds and have a ball ya'll\nEverything's fine it ain't nothing to it\n'Cause we're gonna do it all, don't you know that\n\nWe're just vibin' dancing the night away\nGroovin', vibin', don't stop until the break of day\nWe're just vibin' dancing the night away\nGroovin', vibin', don't stop until the break of day\n\nJust take a minute and catch the vibe\nPut you mind at ease just catch the vibe\nJust take a minute and catch the vibe\nDon't press yourself just catch the vibe\nJust take a minute and catch the vibe\nPut you mind at ease just catch the vibe\nJust take a minute and catch the vibe\nDon't press yourself just catch the vibe\n\nWe're just vibin' dancing the night away\nGroovin', vibin', don't stop until the break of day\n\nJust take a minute and (we're just vibin')\nPut your mind at ease and (we're just vibin')\nJust take a minute and (we're just vibin')\nDon't Press yourself and (we're just vibin')\nJust take a minute and (we're just vibin')\nPut your mind at ease and (we're just vibin')\nJust take a minute and (we're just vibin')\nDon't Press yourself and (we're just vibin')",
 "image": "https://images.rapgenius.com/431f992ffc56a64a469a27f03ce05040.713x713x1.jpg"
}