{
 "title": "Romantic",
 "album": "Ritual of Love",
 "year": "1991-09-10",
 "lyrics": "Ooh\nBaby, baby, baby\nI wanna get romantic\nOh\n\nTurn the lights down\nIt's time to get romantic\nLight a candle\nIt's time to get romantic\nLet's be romantic\n\nTake me in your arms, caress me gently\nOh, I can't get enough, ooh\nThrill me, say the word, I will surrender\nTo your poetic charm, oh\n\n'Cause when the night falls\nI hear seductive voices sing\nRomantic songs of love\nLet's get intimate\n\nTurn the lights down\nIt's time to get romantic\nDo everything romantic now\nLight a candle\nIt's time to get romantic\nThe night has just begun, so baby, let's be romantic\n\nKiss me, I feel the waves of steamy passion\nI'm burning with desire\nBaby, free me from the heat, my heart's on fire\n'Cause I still need your love\n\nUnder the moonlight\nWith the stars shining so bright\nBaby, my mind is on love\nWhen we get home tonight, ooh\n\nTurn the lights down\nIt's time to get romantic\nDo everything romantically\nLight a candle\nIt's time to get romantic\nI wanna get, I wanna get, ooh, romantic\nTurn the lights down (Turn the lights down low)\nIt's time to get romantic (Let's take it slow)\nDo it, do it, do it, do it, oh, you and me\nLight a candle\nIt's time to get romantic\nJust you and me romantically, yeah\n\nJust keep loving me, oh baby (Let's be romantic)\nSweet ecstasy, oh yeah (Let's be romantic)\nBaby, we're all alone\nAnd I got this burning flame that's in my heart\nIt's gonna let the romance start, woo\nOh yeah, romantic, romantic\nIf you want romance\nYou got to work it every chance you get\nTo love your woman right\nThere's no better time, let's start now\nOoh ooh, oh, I, I, I, I\nOoh ooh, I wanna get romantic\nOoh ooh, oh baby\nOh, oh, yeah, yeah, yeah\nLet's get romantic (Ooh), now let's fall in love\n(Let's get romantic)\nMake me surrender to your tender touch (Your tender touch)\nKeep being tender, I can't get enough (Ooh ooh baby)\n(Love me) Let's be romantic\nYour loving, it's just oh so tender\n(It's time to get romantic)\nJust say the word, I will surrender\n(Let's be romantic)\nUnderneath the silver moonlight\n(It's time to get romantic)\nI'll give you my love, love, love, love, love\n(Let's be romantic)\nOh baby, tonight\n\nTurn the lights down\nIt's time to get romantic\nDo everything romantic now\nLight a candle\nIt's time to get romantic",
 "image": "https://images.genius.com/3e6d0981887c3cc666db0dbb54338126.595x598x1.jpg"
}