{
 "title": "Crew",
 "album": "At What Cost",
 "year": "2016-12-16",
 "lyrics": "She see money all around me\nI look like I'm the man, yeah\nBut I was down and out like last week\nTell me where have you been? (Yeah, yeah, yeah)\nYou came out of hiding, girl\nDon't act like I'm your man, you just a fan\nYou don't hold rank (No, no, no, no, no), don't hold no rank\n\nYeah, uh\nDirty ass, Maryland ass nigga\nWith a sick ass mouth and a slick ass flow, uh (Uh-huh)\nGot your bitch around me, nigga, ain't no playin' (Yeah)\nWhen I'm comin' for the kitty, I'm a fool, goddamn\nDo it for my niggas on the coast right there (Right there, yeah)\nDo it for my niggas in the Ghost right now\nNiggas got killed for the boy, live his dreams in the hills\nAnd they watchin' for the boy right now\nGoddamn, what a time, what a year, uh (Goddamn)\nWe are what them young boys fear, uh (Yeah)\nI kill, never been killed, that's real, no lies\nYou can tell that from our peers right now (I want that)\nBet you wanna fuck me now, uh (Yeah, yeah)\nBet you wanna love me down, uh (Yeah, yeah)\nGirl, you can't tie me down like Ray J said\nBut know I'm down, uh\nFreaky deaky, show me somethin', uh\nShake it like you owe me somethin', uh\nPushin' on the pussy like a button\nCame four times, fifth time you gushin', uh\nStill gettin' rowdy in the function, uh (Goddamn)\nBitches on my dick like it's nothin', uh\nEverywhere I go now, always got shit bumpin'\nJumpin', thumpin', jumpin', yeah\n\nHey, nice to meet (Hey), I\u2019m Young Jefe, who you be? (Young Jefe)\nGot my piece in Southeast, got her clappin' to this beat (Clap, clap)\nShe invite me to her crib (Ow!), I walk in, she see my heat (Ow!)\nShe said, \"But I live in the hills\", (Girl) bitch, that\u2019s just the way I sleep (Uh-huh)\nStop that madness, I'm a savage, in traffic with MAC 11\u2019s (Brr)\nBaddest bitch and she Spanish (Ooh!), I fly her to Calabasas\nWe get nasty, I'm her daddy, she know a nigga ain't average (Uh)\nAin't nothin' wrong with fake asses (Uh), bitch, turn around, let's make magic\nI'm geekin', uh-huh, I'm on it (Uh-huh), don't look at me like you want it (No)\nTell 'em that we ain't stuntin' (Uh-uh), in fourth down we ain't puntin' it (Woo!)\nKing of District Columbia, can't come here without a permit (Uh)\nThis shit really a jungle (Goddamn), gorillas and anacondas (Goddamn, goddamn)\n[Chorus: Brent Faiyaz & \nShy Glizzy\n]\nShe see money all around me (\nHey, hey\n)\nI look like I'm the man, yeah (\nYung Jefe holmes\n)\nBut I was down and out like last week\nTell me where have you been? (Yeah, yeah, yeah)\nYou came out of hiding, girl\nDon't act like I'm your man, you just a fan\nYou don't hold rank (No, no, no, no, no), don't hold no rank",
 "image": "https://images.genius.com/0592d0707e460c70351011b010fbba2e.640x640x1.jpg"
}