{
 "title": "Tell Me You Love Me",
 "album": "My Soul",
 "year": null,
 "lyrics": "I unpacked my chest for you\nDo everything that you want me to\nCan't believe I gave you all my love\nWhat in the world was I thinkin' of?\nI just let it all slip away\nWith every minute, hour of the day\nAnd if it really meant to be, just share with me\nWhy do I still feel incomplete?\nTell me, yeah\nI need to know, baby\nI got to know\nTell me, yeah\nTell me that you love me\nIf I give you what you need\nWould you do the same thing for me?\n'Cause I don't want to be alone\nI want you here all night long\n'Cause when you leave me, baby\nI'm thinkin' about you always\nI'm ashamed to say\nHow much I want you to stay\nBaby, tell me, yeah\nI need to know\nSay it now\nI got to know\nTell me that you love me\nNow you see\nI'm not tryin' to make a big fuss over this\nBut I'm just sayin', you need to let me know how you feel sometimes\nSay it, it's not wrong, expressing yourself?\nThat's what wo- women like that, you know what I'm sayin'?\nYou know, you got to tap into your romantic side\nShoot, return the love, baby, return the love\nI need to know, I want to know\nI need to know, I want to know\nI need to know, I want to know\nI need to know, yeah baby\nI got to know, oh, tell me\nTell me that you love me, love me, love me, love me\nThat you love me, love me, love me, love me\nI unpacked my chest for you\nDo everything that you want me to\nCan't believe I gave you all my love",
 "image": "https://images.genius.com/3020dd1105cd8df8da0c96d3da762eba.500x500x1.png"
}