{
 "title": "Internet Money & Gunna - Lemonade ft. Nav & Don Toliver (Deutsche \u00dcbersetzung)",
 "album": null,
 "year": "2020-08-14",
 "lyrics": "Xanax Barren, Selbstm\u00f6rdert\u00fcr, brandneue Tasche\nSchulm\u00e4dchen gibt einem Nigga einen Blowjob in meinen RAFs\nRockstarleben, so viel\u2005Geld,\u2005dass es dich\u2005zum lachen bringt, hey\nDiese Huren, sie\u2005hassen und du kannst nicht vermissen, was du nie hattest, hey, hey\n\nVon dem Saft (Saft), Codein macht mich verr\u00fcckt (Saft)\nKaufte den Coup\u00e9 (Coup\u00e9), wachte auf, das Dach ist nicht da (Yeah)\nEis (Eis), Limonade, mein Nacken ist am drippen\nEis (Eis), Limonade, mein Nacken ist am drippen\n\nAdderall Junge, hab 60mg in meiner Tasche (Adderall)\nMeine Lippen sind versiegelt, ich rede nicht nach dem Sex, ich bin keine Ratte (Nein)\nAn meinen Ohrl\u00e4ppchen habe ich 2 Karat VVS (Bling)\nHab ein Penthouse in der N\u00e4he der Rodeo, weg von dem Stress (Stress)\nAls das ganze Geld, als ich aufwuchs, hatte ich gar nichts (Nothing)\nVoll mit Verr\u00e4tern, mein altes Leben war ekelhaft (Ekelhaft)\nKann es nicht glauben, muss Gott danken, dass ich komfortabel lebe (Danke Gott)\nBekomme Checks, ich glaube ihr nicht, sie sagt, sie w\u00e4re fertig mit mir\nVerbrannte paar Freundschaften und lie\u00df das Feuer den Weg beleuchten (Oh-woah)\nHebe meine F\u00fc\u00dfe hoch, ich verlie\u00df die Projekte in einem Privatjet (Einem Privatjet)\nYeah, ich bin ein gro\u00dfer Kumpel und laufe ohne Leine herum (Oh-oh)\nIch habe Diamanten an mir, yeah, trinke alles mit Fiji\n\nXanax Barren, Selbstm\u00f6rdert\u00fcr, brandneue Tasche\nSchulm\u00e4dchen gibt einem Nigga einen Blowjob in meinen RAFs\nRockstarleben, so viel Geld, dass es dich zum lachen bringt, hey\nDiese Huren, sie hassen und du kannst nicht vermissen, was du nie hattest, hey, hey\n\nVon dem Saft (Saft), Codein macht mich verr\u00fcckt (Saft)\nKaufte den Coup\u00e9 (Coup\u00e9), wachte auf, das Dach ist nicht da (Yeah)\nEis (Eis), Limonade, mein Nacken ist am drippen\nEis (Eis), Limonade, mein Nacken ist am drippen (Hey, Hey)\n\nIch bin ein Rockstar, spiele Gitarre (Yeah), trinke Codein, hey (Hey)\nAdderall, Fentanyl, Xanax Barren, ayy (Hey)\nIch war f\u00fcnfhzehn, ich trank Codein mit meinem besten Freund, ayy (Codein)\nNahm Percocet, Promethazin, ich f\u00fchle mich krass drauf (Promethazin)\nHab ein Raub\u00fcberfall begangen und nahm ein Flugzeug\nIch bleib auf meinen Kriegswegen (Kriegswegen)\nDer Schei\u00df ist riskant, ich muss belohnt werden\nEr belohnte mich mit Reichtum und Bekanntheit (Reichtum und Bekanntheit, nice)\nIch erinnere mich von 50 Cent, ich kann nicht leer zur\u00fcckkommen\nIch wusste, ich war in dieser Szene gefangen (Stuck)\nIch bin loyal und werde mich niemals \u00e4ndern, nah\nIch werde niemals gegen die W\u00fcnsche von anderen was machen (Gegen die W\u00fcnsche von anderen)\nIch werde niemals einen meinen Br\u00fcder verraten\nWenn die Polizei uns festgenommen hat(Nah)\nIch werde niemals eine Hure mehr lieben als meine Mutter\nUnd ich schw\u00f6re auf meinen Namen (Nah)\nIch kann kein Lutscher sein, hasse keinen\nIch w\u00fcnsche, jeder wird bezahlt (Bezahlt)\nWeil wir jeden Tag mehr Geld z\u00e4hlen (Every day)\nWerden high bis wir im Grab sind\n\nXanax Barren, Selbstm\u00f6rdert\u00fcr, brandneue Tasche\nSchulm\u00e4dchen gibt einem Nigga einen Blowjob in meinen RAFs\nRockstarleben, so viel Geld, dass es dich zum lachen bringt, hey\nDiese Huren, sie hassen und du kannst nicht vermissen, was du nie hattest, hey, hey\n\nVon dem Saft (Saft), Codein macht mich verr\u00fcckt (Saft)\nKaufte den Coup\u00e9 (Coup\u00e9), wachte auf, das Dach ist nicht da (Yeah)\nEis (Eis), Limonade, mein Nacken ist am drippen\nEis (Eis), Limonade, mein Nacken ist am drippen\n\nYeah, yeah, yeah",
 "image": "https://images.genius.com/37df218e0fc7ab04cc46196f94865871.1000x1000x1.jpg"
}