{
 "title": "Whatever",
 "album": "EV3",
 "year": "1997-05-13",
 "lyrics": "I'm wanting you too much\nDon't take advantage of\nMy tender heart and everything about me\nIn giving you my trust\nI'm giving you my love\nSo do take care, please be gentle with my heart\n\n(Bum, bum, bum) 'Cause everything I do is 'bout you, baby\n(Bum, bum, bum) Baby, I don't wanna be apart, ooh\n(Bum, bum, bum) I've been loving you from the start\n(Bum, bum, bum) Here's my heart, here's my heart\nEverything I do is all about you, baby\n\nWhatever you do, whatever you think (Whatever)\nI look in your eyes\nYou don't know how my heart aches\nWhatever you say, whatever could mean (Whatever)\nYou're breaking my heart\n\nI want it all the time, I want it every night\nI can't stop thinking, can't stop thinking about you\nI'm burning with desire, my heart and soul on fire\nSo do take care, please be careful with my heart\n\n(Bum, bum, bum) Anything you do, I crave it, baby, baby, baby\n(Bum, bum, bum) I can't get you out of my mind\n(Bum, bum, bum) Loving you I can't deny you're in my heart\n(Bum, bum, bum) Deep inside, everything I do is all about you, baby\n\nWhatever you do, whatever you think (Whatever)\nI look in your eyes\nYou don't know how my heart aches\nWhatever you say, whatever could mean (Whatever could mean)\nYou're breaking my heart\n\nI maybe a fool for you, baby\nWell, I can't help myself\nMaybe I'm too in love\nWhat else can I do but go crazy?\nFor your love, boy, I'd give anything\n(Bum, bum, bum, ho oh oh)\n(Bum, bum, bum, ho oh oh)\n\nWhatever you do, whatever you think\nI look in your eyes\nYou don't know how my heart aches\nWhatever you say, whatever could mean\nYou're breaking my heart\nWhatever you do, whatever you think\nI look in your eyes\nYou don't know how my heart aches\nWhatever you say, whatever could mean\nYou're breaking my heart\nWhatever you do, whatever you think\nI look in your eyes\nYou don't know how my heart aches\nWhatever you say, whatever could mean",
 "image": "https://images.genius.com/928bf468ab22e6cc75b33d895877dcc4.220x220x1.jpg"
}