{
 "title": "Put it On Ya",
 "album": "Da REAList",
 "year": "2008-10-07",
 "lyrics": "Heh...\nYou know they say I'll never sleep, right?\n(They say I'll never sleep!)\nThis one it got number one written all over it\n(This here is number one bay-bay)\nSo let me go and play with it again real quick\n(May I please play with it again?)\nIt's been labelled as being called Plies at his finest\n(This is Plies at his finest)\nBut I'm fin' to fall back right back cause uh\n(Fin' to fall back) I would never do this part right here\nHa hah\n\nShorty I wanna know if you come over\nIf you don't mind girl put your legs up on my shoulders (ooh-wee!)\nDon't lie, I can see it in your eyes\nYou want for you and I to do the freaky things you like\nWhen I put-put-put it on girl, when I put-put-put it on ya\nWhen I put-put-put it on girl, when I put-put-put it on ya\nWhen I put-put-put it on girl, when I put-put-put it on ya\nWhen I put-put-put it on ya, put-put-put it on ya\n\nLet's ride 'round the city, make love in the car\nLet's get on the express way and let me tease you ma\nAnd while you drive baby, I wanna taste your tongue\nPull in the rest area and let me give you some\nYou ever been drivin while your man made you cum\nI wanna hit a stay, I wanna hit and run\nLet's pull the car over, and have a little fun\nThe AC workin, so we ain't gotta bun\n\nCan I lick it, can I stick it, can I touch it, can I grab it\nBaby tell me can I have it (ooh-wee!)\nCan I rub it, can I flip it, can I hold it, can I get it\nAnyway I wanna get it~!\n\n\nIf that don't work for ya I got another idea\nAin't nobody home, so go on come over here\nLet's play hide and seek, in our underwear\nI find you, I can get it right there\nYou find me, then I get bare\nEither way we both win, now that's fair\nWhatever I gotta do to be wit'cha, oh yeah\nYou my queen, I'm your king, now that's a nice pair\n + \n\nLet me grade you, give you a repo't card\nYour first test is, can you get it hard\nShow me how good you communicate when we start\nToday's pop quiz, define yo' hot spot\nWanna see how good yo' balance is on top\nGive you a A+, if you don't stop\nThis a big test, you lookin kinda shocked\nEither you get promoted, or you get dropped\nYour final exam, show me yo' wet box\nAin't no tattle teller, I keep my mouth locked\nMake you an honor student, show me your back shot\nYou passed with flyin colors, ooh that's a nice twat\n + \n\nOoh-wee!",
 "image": "https://images.genius.com/ae7b88ac9a45f699d8285e4ca27b07b6.220x220x1.jpg"
}