{
 "title": "The Anthem",
 "album": "The Boatlift",
 "year": "2007-03-04",
 "lyrics": "Everybody knows this right here\nYour mother, your father, yous sister, your brother\nAbuela y abuelo, everybody sing along\nLatino\nMami el negro, cubano\nMami el negro, puertorrique\u00f1o\nMami el negro, dominicano\nMami el negro, mexicano\n\nMami el negro esta rabioso\nEl quiere tu azucar, y tu no se lo das\nEsa morena esta sabrosa\nY cuando tu la tocas, ella se vuelve loca\nMami el negro esta rabioso\nEl quiere tu azucar, y tu no se lo das\nEsa morena esta sabrosa\nY cuando tu la tocas, ella se vuelve loca\nMami que sera lo que quiere el negro, (a mi que me importa)\nYo lo que quiero es esa loca, (dale dale loca)\nMami que sera lo que quiere el negro, (a mi que me importa)\nYo lo que quiero es esa loca, (dale dale loca)\n\nLet's go\nHey hey, baby give it to me, don't play-play\nShe was like ok-k-k\nStarted clapping her ass to ay bey bey, ay bey bey, ay bey bey\nShe told me that her Mama's Latin, dad's Asian\nAbuela esta loca, abuelos Hatian\nY yo soy cubano and I'm impatient\nSo do me a favor, lets skip conversation\nI just wanna taste ya ASAP\nTake you ASAP to the room ASAP\nZoom zoom ASAP boom boom take that\nOh, I like that\nWhen you fight that\n\nMami el negro esta rabioso\nEl quiere tu azucar, y tu no se lo das\nEsa morena esta sabrosa\nY cuando tu la tocas, ella se vuelve loca\nMami que sera lo que quiere el negro], [(a mi que me importa)\nYo lo que quiero es esa loca], [(dale dale loca)\nMami que sera lo que quiere el negro, (a mi que me importa)\nYo lo que quiero es esa loca, (dale dale loca)\nSee you with your heels\nSexy shirt\nI see you with your man\nYou threw me a smirk\nYou see me with your girls\nYou started to flirt\nBack of the club, hand up her skirt\nHand full of ass\nI'm trying to hold on\nGirls gone wild all night long\nShe had no bra and no thong\nOne more shot\nBaby it's on\nShe's a wild thing\nAnd she loves to do wild things\nSo we did the wild thing\nI'm a freak but I ain't gon' lie\nThat thing was fine man, everybody say\n\nMami el negro esta rabioso\nEl quiere tu azucar, y tu no se lo das\nEsa morena esta sabrosa\nY cuando tu la tocas, ella se vuelve loca\nMami que sera lo que quiere el negro], [(a mi que me importa)\nYo lo que quiero es esa loca], [(dale dale loca)\nMami que sera lo que quiere el negro, (a mi que me importa)\nYo lo que quiero es esa loca, (dale dale loca)\n\nGet nasty, get freaky, you sexy, you fine\nGet nasty, get freaky, you sexy, you fine\nGo go go go girl\nGo go go girl\nGo go go girl\nShake your ass to the beat, shake your ass to the beat\nShake your ass to the beat, shake your ass to the beat\n\nMami el negro esta rabioso\nEl quiere tu azucar, y tu no se lo das\nEsa morena esta sabrosa\nY cuando tu la tocas, ella se vuelve loca\nMami que sera lo que quiere el negro], [(a mi que me importa)\nYo lo que quiero es esa loca], [(dale dale loca)\nMami que sera lo que quiere el negro, (a mi que me importa)\nYo lo que quiero es esa loca, (dale dale loca}\n\nTake it to the floor now\nYo te doy lo tuyo\nAhora, dame lo mio\nYo te doy lo tuyo\nAhora, dame lo mio\nYo te doy lo tuyo\nAhora, dame lo mio, let's go now\nYo te doy lo tuyo\nAhora, dame lo mio\nHey hey hey, let's go ladies",
 "image": "https://images.genius.com/63a51cb5528a1627ac91f13716911dc7.640x640x1.jpg"
}