{
 "title": "Bootylicious",
 "album": "Survivor",
 "year": "2001-05-20",
 "lyrics": "Kelly, can you handle this?\nMichelle, can you handle this?\nBeyonce, can you handle this?\nI don't think they can handle this (Woo)\n\nBetter move, 'cause we've arrived\nLookin' sexy, lookin' fly\nBaddest chick, chick in sight\nDJ, jam tonight\nSpotted me, a tender thang\nThere you are, come on baby\nDon't you wanna dance with me?\nCan you handle, handle me?\n\nYou gotta do much better\nIf you're gonna dance with me tonight\nYou gotta work your jelly\nIf you're gonna dance with me tonight\nRead my lips carefully, if you like what you see\nMove, groove, prove you can hang with me\nBy the looks I got you shook up and scared of me\nBuckle your seatbelt, it's time for takeoff\n\nI don't think you're ready for this jelly\nI don't think you're ready for this jelly\nI don't think you're ready for this\n'Cause my body's too bootylicious for ya, babe\nI don't think you're ready for this jelly (Hey)\nI don't think you're ready for this jelly (Hey)\nI don't think you're ready for this\n'Cause my body's too bootylicious for ya, babe\n\nBaby, can you handle this?\nBaby, can you handle this?\nBaby, can you handle this?\nI don't think you can handle this (Woo)\n\nI'm about to break you off\nH-town goin' hard, read my hips\nSlap my thighs, swing my hair\nSquint my eyes\nLookin' hot, smellin' good\nGroovin' like I'm from the hood\nLook over my shoulder, I blow you a kiss\nCan you handle, handle this?\n\nI don't think you're ready for this jelly\nI don't think you're ready for this jelly\nI don't think you're ready for this\n'Cause my body's too bootylicious for ya, babe\nI don't think you're ready for this jelly\nI don't think you're ready for this jelly\nI don't think you're ready for this\n'Cause my body's too bootylicious for ya, babe\n\nMove your body up and down\nMake your booty touch the ground\nI can't help but wonder why\n'Cause my vibe's too vibealacious for you babe\n\nI shake my jelly at every chance\nWhen I whip with my hips you slip into a trance\nI'm hoping you can handle all this jelly that I have\nNow let's cut a rug while we scat some jazz\n\nPa pa de do da-de\nPa pa de do da-de do\nPa de-de oh\nPa de-de oh\nPow pow pow pow\n\nI don't think you're ready for this jelly (I don't think)\nI don't think you're ready for this jelly (You're ready)\nI don't think you're ready for this\n'Cause my body's too bootylicious for ya, babe\nI don't think you're ready for this jelly\nI don't think you're ready for this jelly\nI don't think you're ready for this\n'Cause my body's too bootylicious for ya, baby\nI don't think you're ready for this jelly\nI don't think you're ready for this jelly\nI don't think you're ready for this\n'Cause my body's too bootylicious for ya, babe\nI don't think you're ready for this jelly (For you, for you, babe)\nI don't think you're ready for this jelly (For you, for you, baby)\nI don't think you're ready for this\n'Cause my body's too bootylicious for ya, babe\nI don't think you're ready for this jelly\nI don't think you're ready for this jelly (I don't think you're ready)\nI don't think you're ready for this\n'Cause my body's too bootylicious for ya, babe\nI don't think you're ready for this jelly\nI don't think you're ready for this jelly\nI don't think you're ready for this\n'Cause my body's too bootylicious for ya, baby",
 "image": "https://images.genius.com/dbc0df442440d5ab9c32bc4e991b68b3.800x800x1.png"
}