{
 "title": "Shawty Is A 10",
 "album": "Love/Hate",
 "year": "2007-07-10",
 "lyrics": "Shawty Rock To The Beat For Ya Boy\nShawty\nDo It\nRock To The Beat For Ya Boy\nRadio Killa, Killa, Killa\nFabolous:\nShawty is the sh-sh-sh-sh\nSugar honey iced tea\nPrettiest one I see\nLittle mama icy\nThey say she a Pisces\nI heard they are feisty\nYou know how to treat her, she\u2019ll be sweeter than a Hi-C\nClean up very nicely, shoes are kinda pricey\nMatch \u2018em up precisely, good jeans nice tee\nLike her food spicy\nAnd she is the same\nHotter than a flame, but I do not know her name\nIs it Keisha? (Ay!)\nIs it Tisha? (Ay!)\nMaybe Lisa? (Ay!)\nOr Teresa? (Ay!)\nIt could be Tia? (Ay!)\nMaybe Aaliyah? (Ay!)\nI guess I\u2019ll find out one day, for now I'mma say (Ay!)\n\nShawty fine, Shawty Tight\nShoulda Stayed There All Night\nWith You (You) With You\nI Missed Ya, Picked Ya\nNow It's Time I\nGet Back up With You(You)Girl With You\nOh Yeah\nWe Used To Kick Up At The Park\nNow She's All Grown Up (up)\nRockin Them Stilettos\nJumpin up Outta That Mercedes Truck (truck)\n\nIt Was Kiesha\nIt Was Sonya\nIt Was Tonya\nIt Was Monique\nIt Was Nece\nIt Was Keke\nNow I See You At 23\nAll I Can Say Is\n\nAhhhhhhhhh, Ahhhhhhhhh\nAnd I Don't Need No Hook For This Hit\nCause Shawty Right There Is a ten, a ten\nShawty you a ten\nA ten\nShawty you a ten\nA ten\nShawty you a ten\nA ten\n\nDior Jeans\nWalk so mean\nBurberry Fragance On My Shirt From When She\nHug Me\nHard As A Rock From When She Touched Me\nThinkin Now That She Would've Loved Me\nWhat It Is, What It Ain't, Tell Me What To Do\nI Know I'm Late But Destiny Brought Me Back To You\nTime went byTurned You Into A Butterfly\nSo I'm here to say hello, Tell Yo *** Goodbye\n\nIt Was Kiesha\nIt Was Sonya\nIt Was Tonya\nIt Was Monique\nIt Was Nece\nIt Was Keke\nNow That I See You At 23\nAll I Can Say Is\n\nAhhhhhhhhhhh, Ahhhhhhhhhh\nAnd I Don't Need No Hook For This Hit\nCause Shawty Right There Is a ten, a ten\nShawty you a ten\nA ten\nShawty you a ten\nA ten\nShawty you a ten\nA ten\n\nIf She Fine, If Shawty Is A Dime\nYou Should Tip Her, You Should Tip Her\nIf She Go, And You Love Her\nYou Should Tip Her, You Should Tip Her\nIf She Fix You Eggs And Grits In The Morning\nYou Should Tip Her, You Should Tip Her\nPancakes With The Bacon On The Side\n(You Should Tip Me, You Should Tip Me)\nShawty Rock To The Beat For Ya Boy\nYeah, Yeah, Yeah\nRock To The Beat For Ya Boy\nNow To See You At 23 All I Can Say Is\n\nAhhhhhhhhhhhh, Aye, Ahhhhhhhh\nAnd I Don't Need No Hook For This Hit\nCause Shawty Right There Is a ten, a ten\nA Ten\nShawty You A Ten\nA Ten\nShawty You A Ten\nA Ten\nShawty You A Ten\nA Ten, Oh Yeah",
 "image": "https://images.genius.com/c2eb4b340a680cb18c09983ceee4d048.450x450x1.jpg"
}